pylastic/__init__.py
pylastic/pylastic.py
pylastic_peshane-0.0.3.dist-info/LICENSE
pylastic_peshane-0.0.3.dist-info/METADATA
pylastic_peshane-0.0.3.dist-info/WHEEL
pylastic_peshane-0.0.3.dist-info/top_level.txt
pylastic_peshane-0.0.3.dist-info/RECORD
