Metadata-Version: 2.1
Name: pylastic-peshane
Version: 0.0.3
Summary: Interact with Jelastic API
Home-page: https://github.com/laurentfufu/pylastic
Author: Laurent Fuentes
Author-email: social@peshane.net
License: UNKNOWN
Platform: UNKNOWN
Classifier: Programming Language :: Python :: 3
Classifier: License :: OSI Approved :: MIT License
Classifier: Operating System :: OS Independent
Requires-Python: >=3.4
Requires-Dist: requests
